kaucherpy/__init__.py
kaucherpy/core/Round.py
kaucherpy/core/__init__.py
kaucherpy/core/fenv.py
kaucherpy/kaucher/Kaucher.py
kaucherpy/kaucher/__init__.py
kaucherpy/support/__init__.py
kaucherpy/support/error.py
kaucherpy/utils/KMath.py
kaucherpy/utils/QualitativeMetrics.py
kaucherpy/utils/__init__.py
kaucherpy-0.1.0.dist-info/METADATA
kaucherpy-0.1.0.dist-info/WHEEL
kaucherpy-0.1.0.dist-info/top_level.txt
kaucherpy-0.1.0.dist-info/RECORD
